{
    "videos": [
      {
        "id": "1",
        "title": "Video Title 1",
        "description": "This is the description for Video 1.",
        "views": 10000,
        "thumbnail": "https://example.com/thumbnail1.jpg"
      },
      {
        "id": "2",
        "title": "Video Title 2",
        "description": "This is the description for Video 2.",
        "views": 20000,
        "thumbnail": "https://example.com/thumbnail2.jpg"
      },
      {
        "id": "3",
        "title": "Video Title 3",
        "description": "This is the description for Video 3.",
        "views": 30000,
        "thumbnail": "https://i.ytimg.com/vi/Pubtjn5QIjg/default.jpg"
      },
      {
        "id": "4",
        "title": "dog",
        "description": "This is the description for Video 3.",
        "views": 300000,
        "thumbnail": "https://example.com/thumbnail3.jpg"
      },
      {
        "id": "5",
        "title": "dogs",
        "description": "This is the description for Video 3.",
        "views": 300,
        "thumbnail": "https://example.com/thumbnail3.jpg"
      },
      {
        "id": "6",
        "title": "trying on dog costumes!! happy holidog",
        "description": "This is the description for Video 3.",
        "views": 3000,
        "thumbnail": "https://i.ytimg.com/vi/bYpItS1jS3Y/default.jpg"
      },
      {
        "id": "8",
        "title": " tiny donkey thinks he's actually a dog  | the dodo",
        "description": "This is the description for Video 3.",
        "views": 300100,
        "thumbnail": "https://i.ytimg.com/vi/MIQKlHSD89E/default.jpg"
      },
      {
        "id": "9",
        "title": "dog owners be like...",
        "description": "This is the description for Video 3.",
        "views": 300089,
        "thumbnail": "https://i.ytimg.com/vi/k3uh0MJeypI/default.jpg"
      },
      {
        "id": "10",
        "title": " meet my dog",
        "description": "This is the description for Video 3.",
        "views": 300002,
        "thumbnail": "https://i.ytimg.com/vi/pfM1F0fBTo8/default.jpg"
      },
      {
        "id": "10",
        "title": " meet my dog",
        "description": "This is the description for Video 3.",
        "views": 300000,
        "thumbnail": "https://i.ytimg.com/vi/pfM1F0fBTo8/default.jpg"
      }
    ]
  }
  